unitcell/__init__.py
unitcell/box.py
unitcell/geometry.py
unitcell/primitive.py
unitcell/struc2.py
unitcell/structures.py
unitcell/unitcell.py
unitcell/utils.py
unitcell-0.1.0.dist-info/LICENSE
unitcell-0.1.0.dist-info/METADATA
unitcell-0.1.0.dist-info/WHEEL
unitcell-0.1.0.dist-info/top_level.txt
unitcell-0.1.0.dist-info/RECORD
