Metadata-Version: 2.1
Name: unitcell
Version: 0.1.0
Summary: Utility package to work and operate on periodic lattices an crystal structures
Author: Angel Yanguas-Gil
Project-URL: Homepage, https://github.com/anglyan/unitcell.git
Keywords: crystal structure,unit cell,periodic lattice
Classifier: Programming Language :: Python :: 3
Classifier: Development Status :: 4 - Beta
Classifier: License :: OSI Approved :: BSD License
Classifier: Operating System :: OS Independent
Classifier: Environment :: Console
Classifier: Topic :: Scientific/Engineering
Classifier: Topic :: Utilities
License-File: LICENSE
